rutpy/__init__.py
rutpy/setup.py
rutpy/core/__init__.py
rutpy/core/rut.py
rutpy-1.0.2.dist-info/METADATA
rutpy-1.0.2.dist-info/WHEEL
rutpy-1.0.2.dist-info/top_level.txt
rutpy-1.0.2.dist-info/RECORD
