Metadata-Version: 2.1
Name: rutpy
Version: 1.0.2
Summary: Librería para el manejo de RUTs chilenos
Author: Valentin Marquez
Author-email: Valentin13.mail@gmail.com
